{
  "$schema": "https://json-schema.org/draft/2020-12/schema",
  "$id": "https://raw.githubusercontent.com/oracle/netsuite-suitecloud-sdk/refs/heads/feature/PDPDEVTOOL-6007-schemas_for_suitecloud_tools/packages/schemas/parent-netsuite-1.0.0.json",
  "title": "Parent schema definition",
  "description": "Parent schema definition",
  "type": "object",
  "oneOf": [
    {
      "type": "object",
      "properties": {
        "CustomField": {
          "$ref": "custom-field-1.0.0.json#/properties"
        },
        "$schema": {
          "type": "string",
          "description": "The schema to verify this document against."
        }
      },
      "required": [
        "CustomField"
      ],
      "additionalProperties": false
    },
    {
      "type": "object",
      "properties": {
        "CustomField": {
          "$ref": "custom-record-1.0.0.json#/properties"
        },
        "$schema": {
          "type": "string",
          "description": "The schema to verify this document against."
        }
      },
      "required": [
        "CustomRecord"
      ],
      "additionalProperties": false
    },
    {
      "type": "object",
      "properties": {
        "CustomField": {
          "$ref": "dataset-builder-plugin-1.0.0.json#/properties"
        },
        "$schema": {
          "type": "string",
          "description": "The schema to verify this document against."
        }
      },
      "required": [
        "DatasetBuilderPlugin"
      ],
      "additionalProperties": false
    },
    {
      "type": "object",
      "properties": {
        "CustomField": {
          "$ref": "fi-connectivity-plugin-1.0.0.json#/properties"
        },
        "$schema": {
          "type": "string",
          "description": "The schema to verify this document against."
        }
      },
      "required": [
        "FiConnectivityPlugin"
      ],
      "additionalProperties": false
    },
    {
      "type": "object",
      "properties": {
        "CustomField": {
          "$ref": "fi-parser-plugin-1.0.0.json#/properties"
        },
        "$schema": {
          "type": "string",
          "description": "The schema to verify this document against."
        }
      },
      "required": [
        "FiParserPlugin"
      ],
      "additionalProperties": false
    },
    {
      "type": "object",
      "properties": {
        "CustomField": {
          "$ref": "integration-1.0.0.json#/properties"
        },
        "$schema": {
          "type": "string",
          "description": "The schema to verify this document against."
        }
      },
      "required": [
        "Integration"
      ],
      "additionalProperties": false
    },
    {
      "type": "object",
      "properties": {
        "CustomField": {
          "$ref": "map-reduce-deployment-1.0.0.json#/properties"
        },
        "$schema": {
          "type": "string",
          "description": "The schema to verify this document against."
        }
      },
      "required": [
        "MapReduceDeployment"
      ],
      "additionalProperties": false
    },
    {
      "type": "object",
      "properties": {
        "CustomField": {
          "$ref": "map-reduce-script-1.0.0.json#/properties"
        },
        "$schema": {
          "type": "string",
          "description": "The schema to verify this document against."
        }
      },
      "required": [
        "MapReduceScript"
      ],
      "additionalProperties": false
    },
    {
      "type": "object",
      "properties": {
        "CustomField": {
          "$ref": "package.json#/properties"
        },
        "$schema": {
          "type": "string",
          "description": "The schema to verify this document against."
        }
      },
      "required": [
        ""
      ],
      "additionalProperties": false
    },
    {
      "type": "object",
      "properties": {
        "CustomField": {
          "$ref": "permission-set-1.0.0.json#/properties"
        },
        "$schema": {
          "type": "string",
          "description": "The schema to verify this document against."
        }
      },
      "required": [
        "PermissionSet"
      ],
      "additionalProperties": false
    },
    {
      "type": "object",
      "properties": {
        "CustomField": {
          "$ref": "sdf-installation-deployment-1.0.0.json#/properties"
        },
        "$schema": {
          "type": "string",
          "description": "The schema to verify this document against."
        }
      },
      "required": [
        "SdfInstallationDeployment"
      ],
      "additionalProperties": false
    },
    {
      "type": "object",
      "properties": {
        "CustomField": {
          "$ref": "sdf-installation-script-1.0.0.json#/properties"
        },
        "$schema": {
          "type": "string",
          "description": "The schema to verify this document against."
        }
      },
      "required": [
        "SdfInstallationScript"
      ],
      "additionalProperties": false
    },
    {
      "type": "object",
      "properties": {
        "CustomField": {
          "$ref": "secret-1.0.0.json#/properties"
        },
        "$schema": {
          "type": "string",
          "description": "The schema to verify this document against."
        }
      },
      "required": [
        "Secret"
      ],
      "additionalProperties": false
    },
    {
      "type": "object",
      "properties": {
        "CustomField": {
          "$ref": "suitecloud-ui-app-1.0.0.json#/properties"
        },
        "$schema": {
          "type": "string",
          "description": "The schema to verify this document against."
        }
      },
      "required": [
        "SuiteCloudUiApp"
      ],
      "additionalProperties": false
    },
    {
      "type": "object",
      "properties": {
        "CustomField": {
          "$ref": "tax-calculation-plugin-1.0.0.json#/properties"
        },
        "$schema": {
          "type": "string",
          "description": "The schema to verify this document against."
        }
      },
      "required": [
        "TaxCalculationPlugin"
      ],
      "additionalProperties": false
    },
    {
      "type": "object",
      "properties": {
        "CustomField": {
          "$ref": "workbook-builder-plugin-1.0.0.json#/properties"
        },
        "$schema": {
          "type": "string",
          "description": "The schema to verify this document against."
        }
      },
      "required": [
        "WorkbookBuilderPlugin"
      ],
      "additionalProperties": false
    }
  ]
}